AUTHORS
MANIFEST.in
Makefile
README.rst
requirements.txt
setup.py
bin/fulcrum
bin/fulcrum.py
fulcrum/__init__.py
fulcrum/const.py
fulcrum/serializer.py
fulcrum/settings.py
fulcrum/template.py
fulcrum/transaction.py
fulcrum/controllers/__init__.py
fulcrum/controllers/cli/__init__.py
fulcrum/controllers/cli/dbshell.py
fulcrum/controllers/cli/loaddata.py
fulcrum/controllers/cli/render.py
fulcrum/controllers/cli/renderdb.py
fulcrum/controllers/cli/shell.py
fulcrum/loaders/__init__.py
fulcrum/loaders/entity.py
fulcrum/loaders/impl/__init__.py
fulcrum/loaders/impl/principal.py
fulcrum/orm/__init__.py
fulcrum/orm/base.py
fulcrum/orm/entity/__init__.py
fulcrum/orm/entity/inodes.py
fulcrum/orm/entity/principals.py
fulcrum/orm/public/__init__.py
fulcrum/orm/public/credentials.py
fulcrum/orm/public/principals.py
fulcrum/orm/state/__init__.py
fulcrum/procedures/__init__.py
fulcrum/procedures/base.py
fulcrum/procedures/public.py
fulcrum/services/__init__.py
fulcrum/services/databasebuild.py
fulcrum/services/datasetimport.py
fulcrum/tests/__init__.py
fulcrum/tests/testdb.py
share/example.yaml
share/scripts/sql/tngems.sql
share/templates/sql/initdb.sql.j2
share/templates/sql/temporal.sql
share/templates/sql/tngems.sql
share/templates/sql/virtual.sql
share/templates/sql/auth/ddl.sql.j2
share/templates/sql/auth/initial_data.sql.j2
share/templates/sql/auth/virtual.sql.j2
share/templates/sql/contact/ddl.sql.j2
share/templates/sql/contact/initial_data.sql.j2
share/templates/sql/contact/procedures.sql.j2
share/templates/sql/contact/virtual.sql.j2
share/templates/sql/iso4217/ddl.sql.j2
share/templates/sql/iso4217/initial_data.sql.j2
share/templates/sql/legalform/ddl.sql.j2
share/templates/sql/party/ddl.sql.j2
share/templates/sql/party/initial_data.sql.j2
share/templates/sql/payment/ddl.sql.j2
share/templates/sql/payment/initial_data.sql.j2
share/templates/sql/product/ddl.sql.j2
share/templates/sql/storage/ddl.sql.j2
share/templates/sql/tld/ddl.sql.j2
tngems_fulcrum.egg-info/PKG-INFO
tngems_fulcrum.egg-info/SOURCES.txt
tngems_fulcrum.egg-info/dependency_links.txt
tngems_fulcrum.egg-info/requires.txt
tngems_fulcrum.egg-info/top_level.txt