Metadata-Version: 1.1
Name: tngems-fulcrum
Version: 0.5.1
Summary: Fulcrum component of the TNG Enterprise Management System
Home-page: http://www.tnginformationsystems.com/
Author: Cochise Ruhulessin
Author-email: cochise.ruhulessin@gmail.com
License: UNKNOWN
Platform: UNKNOWN
Classifier: Development Status :: 3 - Alpha
Classifier: Environment :: Other Environment
Classifier: Intended Audience :: System Administrators
Classifier: Intended Audience :: Developers
Classifier: Operating System :: POSIX :: Linux
Classifier: Programming Language :: Python
Classifier: Programming Language :: Python :: 3.4
Classifier: Programming Language :: SQL
Classifier: Programming Language :: PL/SQL
